truffle/__init__.py
truffle/__main__.py
truffle/api.py
truffle/types.py
truffle/cli/__init__.py
truffle/cli/build.py
truffle/cli/cli.py
truffle/cli/color_argparse.py
truffle/cli/shared.py
truffle/common/__init__.py
truffle/common/logger.py
truffle/platform/__init__.py
truffle/platform/sdk_pb2.py
truffle/platform/sdk_pb2_grpc.py
truffle/runtime/__init__.py
truffle/runtime/base.py
truffle/runtime/decs.py
truffle/runtime/determine_runtime.py
truffle/runtime/public.py
hyphae-0.9.71.dist-info/METADATA
hyphae-0.9.71.dist-info/WHEEL
hyphae-0.9.71.dist-info/entry_points.txt
hyphae-0.9.71.dist-info/top_level.txt
hyphae-0.9.71.dist-info/RECORD
