Metadata-Version: 2.1
Name: hyphae
Version: 0.9.71
Summary: The framework for developing TruffleOS agentic applications
Author: Deepshard
Author-email: accounts@deepshard.org
License: MIT
Requires-Python: >=3.10
Requires-Dist: grpcio==1.69.0
Requires-Dist: grpcio-reflection==1.69.0
Requires-Dist: protobuf==5.29.3
Requires-Dist: requests>=2.32.3
